ReservasHotel/__init__.py
ReservasHotel/rtb_principal.py
ReservasHotel/controladores/__init__.py
ReservasHotel/controladores/rtb_gestionarReservas.py
ReservasHotel/controladores/rtb_login.py
ReservasHotel/controladores/rtb_mostrarReservas.py
ReservasHotel/modelo/__init__.py
ReservasHotel/modelo/datos.py
ReservasHotel/modelo/reservas.db
ReservasHotel/recursos/__init__.py
ReservasHotel/recursos/recursos_rc.py
ReservasHotel/recursos/recursos_rc_rc.py
ReservasHotel/utilidades/__init__.py
ReservasHotel/utilidades/rtb_estilosWidgets.py
ReservasHotel/vistas/__init__.py
ReservasHotel/vistas/rtb_gestionarReservas.py
ReservasHotel/vistas/rtb_login.py
ReservasHotel/vistas/rtb_mostrarReservas.py
ReservasHotel/vistas/rtb_principal.py
rtb_reservashotel-1.1.dist-info/METADATA
rtb_reservashotel-1.1.dist-info/WHEEL
rtb_reservashotel-1.1.dist-info/entry_points.txt
rtb_reservashotel-1.1.dist-info/top_level.txt
rtb_reservashotel-1.1.dist-info/RECORD
