Metadata-Version: 2.4
Name: rtb_ReservasHotel
Version: 1.1
Summary: Gestión de reservas Hotel
Author: Rubén Trillo
Author-email: rtbiota@gmail.com
License: GPL
Requires-Dist: PySide6
Dynamic: author
Dynamic: author-email
Dynamic: license
Dynamic: requires-dist
Dynamic: summary
